hello_world_package/__init__.py
hello_world_package_123-0.0.2.dist-info/METADATA
hello_world_package_123-0.0.2.dist-info/WHEEL
hello_world_package_123-0.0.2.dist-info/top_level.txt
hello_world_package_123-0.0.2.dist-info/RECORD
