Metadata-Version: 2.1
Name: hello-world-package-123
Version: 0.0.2
Summary: hello world package
Home-page: UNKNOWN
Author: idobn
Author-email: <ido.bennatan@gmail.com>
License: UNKNOWN
Keywords: python,hello world
Platform: UNKNOWN
Classifier: Development Status :: 1 - Planning
Classifier: Intended Audience :: Developers
Classifier: Programming Language :: Python :: 3
Classifier: Operating System :: Unix
Classifier: Operating System :: MacOS :: MacOS X
Classifier: Operating System :: Microsoft :: Windows
